gitlab_mcp/__init__.py
gitlab_mcp/server.py
gitlab_mcp/client/__init__.py
gitlab_mcp/client/exceptions.py
gitlab_mcp/client/gitlab_client.py
gitlab_mcp/config/__init__.py
gitlab_mcp/config/settings.py
gitlab_mcp/elicitation/__init__.py
gitlab_mcp/elicitation/registry.py
gitlab_mcp/progress/__init__.py
gitlab_mcp/progress/tracker.py
gitlab_mcp/prompts/__init__.py
gitlab_mcp/prompts/registry.py
gitlab_mcp/resources/__init__.py
gitlab_mcp/resources/handlers.py
gitlab_mcp/resources/registry.py
gitlab_mcp/tasks/__init__.py
gitlab_mcp/tasks/task_manager.py
gitlab_mcp/tools/__init__.py
gitlab_mcp/tools/context.py
gitlab_mcp/tools/groups.py
gitlab_mcp/tools/issues.py
gitlab_mcp/tools/labels.py
gitlab_mcp/tools/merge_requests.py
gitlab_mcp/tools/meta.py
gitlab_mcp/tools/pipelines.py
gitlab_mcp/tools/projects.py
gitlab_mcp/tools/releases.py
gitlab_mcp/tools/repositories.py
gitlab_mcp/tools/snippets.py
gitlab_mcp/tools/users.py
gitlab_mcp/tools/wikis.py
gitlab_mcp/utils/__init__.py
gitlab_mcp/utils/logging.py
python_gitlab_mcp-1.0.0.dist-info/licenses/LICENSE
python_gitlab_mcp-1.0.0.dist-info/METADATA
python_gitlab_mcp-1.0.0.dist-info/WHEEL
python_gitlab_mcp-1.0.0.dist-info/entry_points.txt
python_gitlab_mcp-1.0.0.dist-info/top_level.txt
python_gitlab_mcp-1.0.0.dist-info/RECORD
