Metadata-Version: 2.4
Name: python-gitlab-mcp
Version: 1.0.0
Summary: Production-ready Model Context Protocol server for GitLab - 87 tools, 14 prompts, 13 resources
Author-email: Wade Woolwine <wade.woolwine@gmail.com>
Maintainer-email: Wade Woolwine <wade.woolwine@gmail.com>
License-Expression: MIT
Project-URL: Homepage, https://github.com/wadew/gitlab-mcp
Project-URL: Documentation, https://github.com/wadew/gitlab-mcp#documentation
Project-URL: Repository, https://github.com/wadew/gitlab-mcp.git
Project-URL: Issues, https://github.com/wadew/gitlab-mcp/issues
Project-URL: Changelog, https://github.com/wadew/gitlab-mcp/blob/main/CHANGELOG.md
Keywords: gitlab,mcp,model-context-protocol,ai,llm,claude,anthropic,devops,ci-cd,automation,api-client,async,type-safe
Classifier: Development Status :: 5 - Production/Stable
Classifier: Intended Audience :: Developers
Classifier: Programming Language :: Python :: 3
Classifier: Programming Language :: Python :: 3.10
Classifier: Programming Language :: Python :: 3.11
Classifier: Programming Language :: Python :: 3.12
Classifier: Topic :: Software Development :: Libraries :: Python Modules
Classifier: Topic :: Software Development :: Version Control :: Git
Classifier: Topic :: System :: Systems Administration
Classifier: Framework :: AsyncIO
Classifier: Typing :: Typed
Classifier: Operating System :: OS Independent
Requires-Python: >=3.10
License-File: LICENSE
Requires-Dist: mcp>=1.25.0
Requires-Dist: python-gitlab>=7.1.0
Requires-Dist: pydantic>=2.12.5
Requires-Dist: python-dotenv>=1.2.1
Requires-Dist: httpx>=0.28.1
Requires-Dist: starlette>=0.50.0
Requires-Dist: uvicorn>=0.40.0
Provides-Extra: dev
Requires-Dist: pytest>=9.0.2; extra == "dev"
Requires-Dist: pytest-cov>=7.0.0; extra == "dev"
Requires-Dist: pytest-asyncio>=1.3.0; extra == "dev"
Requires-Dist: pytest-mock>=3.15.1; extra == "dev"
Requires-Dist: black>=25.12.0; extra == "dev"
Requires-Dist: ruff>=0.14.10; extra == "dev"
Requires-Dist: mypy>=1.19.1; extra == "dev"
Requires-Dist: types-requests; extra == "dev"
Requires-Dist: pre-commit>=4.0.0; extra == "dev"
Requires-Dist: build>=1.2.0; extra == "dev"
Requires-Dist: twine>=6.0.0; extra == "dev"
Dynamic: license-file
